pydantic_config_ui/__init__.py
pydantic_config_ui/config_dialog.ui
pydantic_config_ui/configuration_common.py
pydantic_config_ui/configuration_editor.py
pydantic_config_ui/configuration_exec.py
pydantic_config_ui/field_array.py
pydantic_config_ui/field_checkbox.py
pydantic_config_ui/field_file_select.py
pydantic_config_ui/field_folder_select.py
pydantic_config_ui/field_hidden.py
pydantic_config_ui/field_input.py
pydantic_config_ui/i18n/pydantic_config_ui_de_DE.qm
pydantic_config_ui/i18n/pydantic_config_ui_de_DE.ts
pydantic_config_ui/i18n/pydantic_config_ui_en_US.qm
pydantic_config_ui/i18n/pydantic_config_ui_en_US.ts
pydantic_config_ui/recent_combobox.py
pydantic_config_ui/ui_config_dialog.py
pydantic_config_ui-0.6.1.dist-info/LICENSE
pydantic_config_ui-0.6.1.dist-info/METADATA
pydantic_config_ui-0.6.1.dist-info/WHEEL
pydantic_config_ui-0.6.1.dist-info/RECORD
