Metadata-Version: 2.3
Name: pydantic-config-ui
Version: 0.6.1
Summary: Generate a QDialog from a Pydantic class using PySide 6
License: MIT
Keywords: pyside6,pydantic2,qt,configuration
Author: Steffen Köhler
Author-email: stefen.koehler@gmail.com
Requires-Python: >=3.9,<3.14
Classifier: Development Status :: 4 - Beta
Classifier: Framework :: Pydantic :: 2
Classifier: Intended Audience :: End Users/Desktop
Classifier: License :: OSI Approved :: MIT License
Classifier: Operating System :: OS Independent
Classifier: Programming Language :: Python :: 3
Classifier: Programming Language :: Python :: 3.9
Classifier: Programming Language :: Python :: 3.10
Classifier: Programming Language :: Python :: 3.11
Classifier: Programming Language :: Python :: 3.12
Classifier: Programming Language :: Python :: 3.13
Requires-Dist: PySide6 (>=6.8)
Requires-Dist: pydantic (>=2.1)
Project-URL: Documentation, https://mosling.gitlab.io/pydantic-config-ui-docs
Project-URL: Homepage, https://gitlab.com/mosling/pydantic-config-ui
